{
    "billing.bundle.js": "/assets/frappe/dist/js/billing.bundle.3M2NKQ7F.js",
    "bootstrap-4-web.bundle.js": "/assets/frappe/dist/js/bootstrap-4-web.bundle.AZ67VXZX.js",
    "calendar.bundle.js": "/assets/frappe/dist/js/calendar.bundle.CUFNYKMX.js",
    "controls.bundle.js": "/assets/frappe/dist/js/controls.bundle.3FYRNEBL.js",
    "data_import_tools.bundle.js": "/assets/frappe/dist/js/data_import_tools.bundle.2FYWI47H.js",
    "desk.bundle.js": "/assets/frappe/dist/js/desk.bundle.V5GHXCC6.js",
    "dialog.bundle.js": "/assets/frappe/dist/js/dialog.bundle.7AG42GA6.js",
    "form.bundle.js": "/assets/frappe/dist/js/form.bundle.TFTPNYYA.js",
    "frappe-web.bundle.js": "/assets/frappe/dist/js/frappe-web.bundle.4KGM4CRK.js",
    "libs.bundle.js": "/assets/frappe/dist/js/libs.bundle.LLRFRX7M.js",
    "list.bundle.js": "/assets/frappe/dist/js/list.bundle.TLVIMEXW.js",
    "logtypes.bundle.js": "/assets/frappe/dist/js/logtypes.bundle.FWKQ24YH.js",
    "onboarding_tours.bundle.js": "/assets/frappe/dist/js/onboarding_tours.bundle.P7QYMXLW.js",
    "photoswipe.bundle.js": "/assets/frappe/dist/js/photoswipe.bundle.2BDW3PAH.js",
    "report.bundle.js": "/assets/frappe/dist/js/report.bundle.D3XSRA77.js",
    "sentry.bundle.js": "/assets/frappe/dist/js/sentry.bundle.SI3DB3BY.js",
    "telemetry.bundle.js": "/assets/frappe/dist/js/telemetry.bundle.ZJBT5ETW.js",
    "video_player.bundle.js": "/assets/frappe/dist/js/video_player.bundle.IOEIXC2G.js",
    "web_form.bundle.js": "/assets/frappe/dist/js/web_form.bundle.RCE7ZNYE.js",
    "form_builder.bundle.js": "/assets/frappe/dist/js/form_builder.bundle.2GFSN2JA.js",
    "print_format_builder.bundle.js": "/assets/frappe/dist/js/print_format_builder.bundle.E53VUOQE.js",
    "workflow_builder.bundle.js": "/assets/frappe/dist/js/workflow_builder.bundle.P2K5FM7T.js",
    "build_events.bundle.js": "/assets/frappe/dist/js/build_events.bundle.MFER6TZC.js",
    "file_uploader.bundle.js": "/assets/frappe/dist/js/file_uploader.bundle.VGN7REND.js",
    "kanban_board.bundle.js": "/assets/frappe/dist/js/kanban_board.bundle.L56XYUZN.js",
    "desk.bundle.css": "/assets/frappe/dist/css/desk.bundle.7HTJUAQN.css",
    "email.bundle.css": "/assets/frappe/dist/css/email.bundle.EMVYAALU.css",
    "login.bundle.css": "/assets/frappe/dist/css/login.bundle.5HAP3USH.css",
    "print.bundle.css": "/assets/frappe/dist/css/print.bundle.LMIA53FZ.css",
    "print_format.bundle.css": "/assets/frappe/dist/css/print_format.bundle.4O56U4A6.css",
    "report.bundle.css": "/assets/frappe/dist/css/report.bundle.RPKV43PR.css",
    "web_form.bundle.css": "/assets/frappe/dist/css/web_form.bundle.2BBVWP2J.css",
    "website.bundle.css": "/assets/frappe/dist/css/website.bundle.NEF2WRA7.css"
}